dicom_parser/__init__.py
dicom_parser/data_element.py
dicom_parser/header.py
dicom_parser/image.py
dicom_parser/messages.py
dicom_parser/series.py
dicom_parser/data_elements/__init__.py
dicom_parser/data_elements/age_string.py
dicom_parser/data_elements/application_entity.py
dicom_parser/data_elements/attribute_tag.py
dicom_parser/data_elements/code_string.py
dicom_parser/data_elements/date.py
dicom_parser/data_elements/date_time.py
dicom_parser/data_elements/decimal_string.py
dicom_parser/data_elements/floating_point_double.py
dicom_parser/data_elements/floating_point_single.py
dicom_parser/data_elements/integer_string.py
dicom_parser/data_elements/long_string.py
dicom_parser/data_elements/long_text.py
dicom_parser/data_elements/messages.py
dicom_parser/data_elements/other_64bit_very_long.py
dicom_parser/data_elements/other_byte.py
dicom_parser/data_elements/other_double.py
dicom_parser/data_elements/other_float.py
dicom_parser/data_elements/other_long.py
dicom_parser/data_elements/other_word.py
dicom_parser/data_elements/person_name.py
dicom_parser/data_elements/private_data_element.py
dicom_parser/data_elements/sequence_of_items.py
dicom_parser/data_elements/short_string.py
dicom_parser/data_elements/short_text.py
dicom_parser/data_elements/signed_64bit_very_long.py
dicom_parser/data_elements/signed_long.py
dicom_parser/data_elements/signed_short.py
dicom_parser/data_elements/time.py
dicom_parser/data_elements/unique_identifier.py
dicom_parser/data_elements/unlimited_characters.py
dicom_parser/data_elements/unlimited_text.py
dicom_parser/data_elements/unsigned_64bit_very_long.py
dicom_parser/data_elements/unsigned_long.py
dicom_parser/data_elements/unsigned_short.py
dicom_parser/data_elements/url.py
dicom_parser/utils/__init__.py
dicom_parser/utils/choice_enum.py
dicom_parser/utils/exceptions.py
dicom_parser/utils/format_header_df.py
dicom_parser/utils/image_generator.py
dicom_parser/utils/messages.py
dicom_parser/utils/mime_generator.py
dicom_parser-1.2.3.dist-info/LICENSE
dicom_parser-1.2.3.dist-info/METADATA
dicom_parser-1.2.3.dist-info/WHEEL
dicom_parser-1.2.3.dist-info/top_level.txt
dicom_parser-1.2.3.dist-info/RECORD
