Metadata-Version: 2.1
Name: dicom-parser
Version: 1.2.3
Summary: DICOM files parser meant to facilitate data access.
Home-page: https://github.com/ZviBaratz/dicom_parser
Author: Zvi Baratz
Author-email: z.baratz@gmail.com
License: MIT
Project-URL: Source, https://github.com/ZviBaratz/dicom_parser/
Project-URL: Documentation, https://dicom-parser.readthedocs.io/en/latest/
Project-URL: Bug Reports, https://github.com/ZviBaratz/dicom_parser/issues/
Keywords: dicom,dcm,mri,ct,radiology
Classifier: Development Status :: 5 - Production/Stable
Classifier: Intended Audience :: Science/Research
Classifier: Intended Audience :: Healthcare Industry
Classifier: License :: OSI Approved :: MIT License
Classifier: Operating System :: OS Independent
Classifier: Programming Language :: Python :: 3
Classifier: Programming Language :: Python :: 3.6
Classifier: Programming Language :: Python :: 3.7
Classifier: Programming Language :: Python :: 3.8
Classifier: Programming Language :: Python :: 3.9
Classifier: Programming Language :: Python :: 3.10
Classifier: Programming Language :: Python :: 3 :: Only
Requires-Python: <4,>=3.6
License-File: LICENSE
Requires-Dist: pydicom (<2.4,>=2.1)
Requires-Dist: numpy ; python_version == "3.6"
Requires-Dist: numpy (~=1.21) ; python_version > "3.6"
Provides-Extra: all
Requires-Dist: black (~=22.1) ; extra == 'all'
Requires-Dist: doc8 (~=0.10) ; extra == 'all'
Requires-Dist: flake8 (~=4.0) ; extra == 'all'
Requires-Dist: ipython ; extra == 'all'
Requires-Dist: isort (~=5.10) ; extra == 'all'
Requires-Dist: pre-commit ; extra == 'all'
Requires-Dist: pre-commit-hooks ; extra == 'all'
Requires-Dist: sphinx (~=4.4) ; extra == 'all'
Requires-Dist: sphinx-rtd-theme (~=1.0) ; extra == 'all'
Requires-Dist: coverage[toml] (>=6.2) ; extra == 'all'
Requires-Dist: pytest (~=7.0) ; extra == 'all'
Requires-Dist: tox (~=3.24) ; extra == 'all'
Requires-Dist: build ; extra == 'all'
Requires-Dist: twine ; extra == 'all'
Requires-Dist: jinja2 ; extra == 'all'
Requires-Dist: pandas ; extra == 'all'
Requires-Dist: python-magic (~=0.4) ; (platform_system != "Windows") and extra == 'all'
Requires-Dist: pickle5 (~=0.0) ; (python_version <= "3.7") and extra == 'all'
Provides-Extra: dev
Requires-Dist: black (~=22.1) ; extra == 'dev'
Requires-Dist: doc8 (~=0.10) ; extra == 'dev'
Requires-Dist: flake8 (~=4.0) ; extra == 'dev'
Requires-Dist: ipython ; extra == 'dev'
Requires-Dist: isort (~=5.10) ; extra == 'dev'
Requires-Dist: pre-commit ; extra == 'dev'
Requires-Dist: pre-commit-hooks ; extra == 'dev'
Requires-Dist: sphinx (~=4.4) ; extra == 'dev'
Requires-Dist: sphinx-rtd-theme (~=1.0) ; extra == 'dev'
Requires-Dist: coverage[toml] (>=6.2) ; extra == 'dev'
Requires-Dist: pytest (~=7.0) ; extra == 'dev'
Requires-Dist: tox (~=3.24) ; extra == 'dev'
Requires-Dist: python-magic (~=0.4) ; (platform_system != "Windows") and extra == 'dev'
Requires-Dist: pickle5 (~=0.0) ; (python_version <= "3.7") and extra == 'dev'
Provides-Extra: dist
Requires-Dist: build ; extra == 'dist'
Requires-Dist: twine ; extra == 'dist'
Provides-Extra: docs
Requires-Dist: sphinx (~=4.4) ; extra == 'docs'
Requires-Dist: sphinx-rtd-theme (~=1.0) ; extra == 'docs'
Provides-Extra: magic
Requires-Dist: python-magic (~=0.4) ; (platform_system != "Windows") and extra == 'magic'
Provides-Extra: pandas
Requires-Dist: jinja2 ; extra == 'pandas'
Requires-Dist: pandas ; extra == 'pandas'
Provides-Extra: test
Requires-Dist: coverage[toml] (>=6.2) ; extra == 'test'
Requires-Dist: pytest (~=7.0) ; extra == 'test'
Requires-Dist: tox (~=3.24) ; extra == 'test'
Requires-Dist: python-magic (~=0.4) ; (platform_system != "Windows") and extra == 'test'
Requires-Dist: pickle5 (~=0.0) ; (python_version <= "3.7") and extra == 'test'
